MANIFEST.in
README.rst
setup.py
collective/__init__.py
collective.js.ui.multiselect.egg-info/PKG-INFO
collective.js.ui.multiselect.egg-info/SOURCES.txt
collective.js.ui.multiselect.egg-info/dependency_links.txt
collective.js.ui.multiselect.egg-info/entry_points.txt
collective.js.ui.multiselect.egg-info/namespace_packages.txt
collective.js.ui.multiselect.egg-info/not-zip-safe
collective.js.ui.multiselect.egg-info/requires.txt
collective.js.ui.multiselect.egg-info/top_level.txt
collective/js/__init__.py
collective/js/ui/__init__.py
collective/js/ui/multiselect/__init__.py
collective/js/ui/multiselect/configure.zcml
collective/js/ui/multiselect/jquery.ui.multiselect.js
collective/js/ui/multiselect/ui.multiselect.css
collective/js/ui/multiselect/profiles/default/cssregistry.xml
collective/js/ui/multiselect/profiles/default/jsregistry.xml
collective/js/ui/multiselect/profiles/default/metadata.xml
collective/js/ui/multiselect/upgrades/__init__.py
collective/js/ui/multiselect/upgrades/configure.zcml
collective/js/ui/multiselect/upgrades/to1001.py
collective/js/ui/multiselect/upgrades/profiles/1001/cssregistry.xml
docs/HISTORY.txt
docs/LICENSE.GPL
docs/LICENSE.txt