Metadata-Version: 1.1
Name: collective.js.ui.multiselect
Version: 1.0.1
Summary: Integrates the multiselect widget into plone.
Home-page: https://github.com/4teamwork/collective.js.ui.multiselect
Author: Elio Schmutz
Author-email: mailto:info@4teamwork.ch
License: GPL2
Keywords: jquery ui multiselect plone
Platform: UNKNOWN
Classifier: Framework :: Plone
Classifier: Framework :: Plone :: 4.0
Classifier: Framework :: Plone :: 4.1
Classifier: License :: OSI Approved :: GNU General Public License (GPL)
Classifier: Programming Language :: Python
Classifier: Programming Language :: Python :: 2.6
